matrix_rain/__init__.py
matrix_rain/main.py
matrix_rain-1.0.2.dist-info/entry_points.txt
matrix_rain-1.0.2.dist-info/LICENSE.md
matrix_rain-1.0.2.dist-info/WHEEL
matrix_rain-1.0.2.dist-info/METADATA
matrix_rain-1.0.2.dist-info/RECORD
