Metadata-Version: 2.1
Name: matrix-rain
Version: 1.0.2
Summary: 
Author: principle105
Author-email: principle105@gmail.com
Requires-Python: >=3.10,<4.0
Classifier: Programming Language :: Python :: 3
Classifier: Programming Language :: Python :: 3.10
Requires-Dist: rich (>=12.6.0,<13.0.0)
Requires-Dist: typer (>=0.6.1,<0.7.0)
